Tests/__init__.py
Tests/test_geocode.py
geocode/__init__.py
geocode/bng2latlon.py
geocode/cache_manager.py
geocode/cpo.py
geocode/eurostat.py
geocode/geocode.py
geocode/gmaps.py
geocode/latlons2gsp.py
geocode/latlons2llsoa.py
geocode/neso.py
geocode/ons_nrs.py
geocode/postcodes2latlon.py
geocode/utilities.py
geocode/version.py
geocode/cache/__init__.py
geocode/code_point_open/__init__.py
geocode/code_point_open/codepo_gb.zip
geocode/ons/PCD_OA_LSOA_MSOA_LAD_MAY22_UK_LU.zip
geocode/ons/__init__.py
geocode/ons/constituency_centroids.psv
geocode/ons/constituency_centroids_Dec2020.psv
geocode/ons/lad_centroids_May2021.psv
geocode/ons/nrs.zip
geocode_ss-1.4.dist-info/licenses/LICENSE
geocode_ss-1.4.dist-info/METADATA
geocode_ss-1.4.dist-info/WHEEL
geocode_ss-1.4.dist-info/entry_points.txt
geocode_ss-1.4.dist-info/top_level.txt
geocode_ss-1.4.dist-info/RECORD
