Metadata-Version: 2.4
Name: geocode-ss
Version: 1.4
Summary: Geocode postcodes, addresses or LLSOA using the Code Point Open database and GMaps API.
Home-page: https://github.com/SheffieldSolar/Geocode
Download-URL: https://github.com/SheffieldSolar/Geocode/releases
Author: Jamie Taylor
Author-email: jamie.taylor@sheffield.ac.uk
License: MIT
Keywords: geocode
Classifier: Development Status :: 5 - Production/Stable
Classifier: Intended Audience :: Developers
Classifier: Intended Audience :: Science/Research
Classifier: Intended Audience :: System Administrators
Classifier: Topic :: Database :: Database Engines/Servers
Classifier: Topic :: Utilities
Classifier: License :: Other/Proprietary License
Classifier: Programming Language :: Python :: 3 :: Only
Classifier: Programming Language :: Python :: 3.11
Classifier: Programming Language :: Python :: 3.12
Classifier: Programming Language :: Python :: 3.13
License-File: LICENSE
Requires-Dist: numpy
Requires-Dist: pandas
Requires-Dist: googlemaps
Requires-Dist: requests
Requires-Dist: shapely
Requires-Dist: pyshp
Requires-Dist: pyproj
Requires-Dist: geopandas
Provides-Extra: dev
Requires-Dist: pylint; extra == "dev"
Requires-Dist: sphinx; extra == "dev"
Requires-Dist: numpydoc; extra == "dev"
Requires-Dist: sphinx_rtd_theme; extra == "dev"
Dynamic: author
Dynamic: author-email
Dynamic: classifier
Dynamic: description
Dynamic: description-content-type
Dynamic: download-url
Dynamic: home-page
Dynamic: keywords
Dynamic: license
Dynamic: license-file
Dynamic: provides-extra
Dynamic: requires-dist
Dynamic: summary
